varo_to_monarch/__init__.py
varo_to_monarch/cli.py
varo_to_monarch/constants.py
varo_to_monarch/extractors.py
varo_to_monarch/gui.py
varo_to_monarch/processing.py
varo_to_monarch/utils.py
varo_to_monarch-0.3.3.dist-info/licenses/LICENSE
varo_to_monarch-0.3.3.dist-info/METADATA
varo_to_monarch-0.3.3.dist-info/WHEEL
varo_to_monarch-0.3.3.dist-info/entry_points.txt
varo_to_monarch-0.3.3.dist-info/top_level.txt
varo_to_monarch-0.3.3.dist-info/RECORD
