Metadata-Version: 2.4
Name: varo-to-monarch
Version: 0.3.3
Summary: Convert Varo Bank PDF statements to Monarch Money CSV format
Author-email: blacksuan19 <py@aolabs.dev>
Project-URL: Homepage, https://github.com/blacksuan19/varo-to-monarch
Project-URL: Repository, https://github.com/blacksuan19/varo-to-monarch
Project-URL: Issues, https://github.com/blacksuan19/varo-to-monarch/issues
Keywords: varo,monarch,bank,statement,pdf,csv,converter
Classifier: Development Status :: 4 - Beta
Classifier: Intended Audience :: End Users/Desktop
Classifier: Programming Language :: Python :: 3
Classifier: Programming Language :: Python :: 3.8
Classifier: Programming Language :: Python :: 3.9
Classifier: Programming Language :: Python :: 3.10
Classifier: Programming Language :: Python :: 3.11
Classifier: Programming Language :: Python :: 3.12
Classifier: Topic :: Office/Business :: Financial
Classifier: Topic :: Utilities
Requires-Python: >=3.8
License-File: LICENSE
Requires-Dist: pymupdf
Requires-Dist: pandas
Requires-Dist: pdfplumber
Requires-Dist: typer
Requires-Dist: rich
Requires-Dist: pyside6
Requires-Dist: pymupdf_layout
Provides-Extra: dev
Requires-Dist: black; extra == "dev"
Requires-Dist: ruff; extra == "dev"
Requires-Dist: mypy; extra == "dev"
Requires-Dist: build; extra == "dev"
Requires-Dist: bumpver; extra == "dev"
Requires-Dist: pyinstaller; extra == "dev"
Dynamic: license-file
